miraclecodetestnew/__init__.py
miraclecodetestnew/add.py
miraclecodetestnew/subtract.py
miraclecodetestnew/extras/__init__.py
miraclecodetestnew/extras/divide.py
miraclecodetestnew/extras/multiply.py
miraclecodetestnew-0.0.1.dist-info/METADATA
miraclecodetestnew-0.0.1.dist-info/WHEEL
miraclecodetestnew-0.0.1.dist-info/top_level.txt
miraclecodetestnew-0.0.1.dist-info/RECORD
