Metadata-Version: 2.1
Name: miraclecodetestnew
Version: 0.0.1
Summary: Miraclecodetestnew Python package
Home-page: UNKNOWN
Author: Rajesh
Author-email: <rajeshthangaraj1@gmail.com>
License: UNKNOWN
Keywords: python,first package
Platform: UNKNOWN
Classifier: Development Status :: 3 - Alpha
Classifier: Intended Audience :: Education
Classifier: Programming Language :: Python :: 2
Classifier: Programming Language :: Python :: 3
Classifier: Operating System :: MacOS :: MacOS X
Classifier: Operating System :: Microsoft :: Windows
